cog_generator/__init__.py
cog_generator/cog_generator.py
cog_generator/utils.py
cog_generator-0.0.1.dist-info/LICENSE
cog_generator-0.0.1.dist-info/METADATA
cog_generator-0.0.1.dist-info/WHEEL
cog_generator-0.0.1.dist-info/top_level.txt
cog_generator-0.0.1.dist-info/RECORD
