Metadata-Version: 2.1
Name: cog_generator
Version: 0.0.1
Summary: This package wraps around the native GDAL library which enables Cloud Optimized GeoTiffs generation at ease into your Python projects.
Home-page: https://github.com/iamrajbhattarai/cog_generator
Author: Raj Bhattarai
Author-email: raj.bhattarai222@gmail.com
License: GPLv3
Keywords: COG,GeoTiff
Classifier: Development Status :: 3 - Alpha
Classifier: Intended Audience :: Developers
Classifier: Topic :: Scientific/Engineering :: GIS
Classifier: License :: OSI Approved :: GNU Affero General Public License v3
Classifier: Programming Language :: Python :: 3.8
License-File: LICENSE
Requires-Dist: GDAL >=3.4.1
